_turbo_kernels.cpython-310-x86_64-linux-gnu.so
mosaicml_turbo-0.0.9.dist-info/WHEEL
mosaicml_turbo-0.0.9.dist-info/LICENSE.txt
mosaicml_turbo-0.0.9.dist-info/top_level.txt
mosaicml_turbo-0.0.9.dist-info/RECORD
mosaicml_turbo-0.0.9.dist-info/METADATA
turbo/__init__.py
turbo/_add.py
turbo/_quantize.py
turbo/_codecs.py
turbo/lion8b.py
turbo/_lion.py
turbo/_comms.py
turbo/_experiment.py
turbo/_utils.py
mosaicml_turbo.libs/libcudart-9335f6a2.so.12.1.105
mosaicml_turbo.libs/libgomp-a34b3233-570455c2.so.1
mosaicml_turbo.libs/libnvToolsExt-847d78f2-c48e14b1.so.1
mosaicml_turbo.libs/libshm-291abe19.so
mosaicml_turbo.libs/libcudart-9335f6a2-d5330808.so.12
mosaicml_turbo.libs/libcudnn-ce8aa8f7.so.8
mosaicml_turbo.libs/libc10_cuda-5dee4b62.so
mosaicml_turbo.libs/libtorch-eca1a085.so
