Metadata-Version: 2.1
Name: mosaicml-turbo
Version: 0.0.9
Summary: Custom kernels
Home-page: https://github.com/dblalock/turbo
Author: dblalock
Author-email: davis@mosaicml.com
Classifier: Programming Language :: Python :: 3
Requires-Python: >=3.7
License-File: LICENSE.txt
Provides-Extra: dev
Requires-Dist: pytest ; extra == 'dev'
Requires-Dist: docformatter ; extra == 'dev'
Requires-Dist: isort ; extra == 'dev'
Requires-Dist: pyright ; extra == 'dev'
Requires-Dist: toml ; extra == 'dev'
Requires-Dist: yapf ; extra == 'dev'
Requires-Dist: auditwheel ; extra == 'dev'
Requires-Dist: patchelf ; extra == 'dev'
Requires-Dist: twine ; extra == 'dev'
Requires-Dist: mosaicml ; extra == 'dev'
Requires-Dist: pandas ; extra == 'dev'
